ryoma_ai/__init__.py
ryoma_ai/client.py
ryoma_ai/states.py
ryoma_ai/agent/__init__.py
ryoma_ai/agent/arrow_agent.py
ryoma_ai/agent/base.py
ryoma_ai/agent/chat_agent.py
ryoma_ai/agent/embedding.py
ryoma_ai/agent/factory.py
ryoma_ai/agent/kernel_node.py
ryoma_ai/agent/pandas_agent.py
ryoma_ai/agent/python_agent.py
ryoma_ai/agent/resource_registry.py
ryoma_ai/agent/spark_agent.py
ryoma_ai/agent/sql.py
ryoma_ai/agent/validator.py
ryoma_ai/agent/workflow.py
ryoma_ai/api/__init__.py
ryoma_ai/api/agent_manager.py
ryoma_ai/api/vector_index_manager.py
ryoma_ai/datasource/__init__.py
ryoma_ai/datasource/base.py
ryoma_ai/datasource/bigquery.py
ryoma_ai/datasource/dataplex.py
ryoma_ai/datasource/dataplex_loader.py
ryoma_ai/datasource/duckdb.py
ryoma_ai/datasource/factory.py
ryoma_ai/datasource/file.py
ryoma_ai/datasource/metadata.py
ryoma_ai/datasource/mysql.py
ryoma_ai/datasource/nosql.py
ryoma_ai/datasource/postgres.py
ryoma_ai/datasource/snowflake.py
ryoma_ai/datasource/sqlite.py
ryoma_ai/embedding/__init__.py
ryoma_ai/embedding/client.py
ryoma_ai/embedding/config.py
ryoma_ai/embedding/factory.py
ryoma_ai/llm/__init__.py
ryoma_ai/llm/provider.py
ryoma_ai/models/agent.py
ryoma_ai/prompt/ExampleFormatTemplate.py
ryoma_ai/prompt/ExampleSelectorTemplate.py
ryoma_ai/prompt/PromptICLTemplate.py
ryoma_ai/prompt/PromptReprTemplate.py
ryoma_ai/prompt/__init__.py
ryoma_ai/prompt/base.py
ryoma_ai/prompt/enums.py
ryoma_ai/prompt/prompt_builder.py
ryoma_ai/prompt/prompt_template.py
ryoma_ai/prompt/utils.py
ryoma_ai/prompt/templates/dataset1.json
ryoma_ai/prompt/templates/dataset2.json
ryoma_ai/prompt/templates/formatted_data.json
ryoma_ai/prompt/templates/templates_parser.py
ryoma_ai/tool/__init__.py
ryoma_ai/tool/pandas_tool.py
ryoma_ai/tool/pyarrow_tool.py
ryoma_ai/tool/python_tool.py
ryoma_ai/tool/spark_tool.py
ryoma_ai/tool/sql_tool.py
ryoma_ai/vector_store/__init__.py
ryoma_ai/vector_store/base.py
ryoma_ai/vector_store/config.py
ryoma_ai/vector_store/factory.py
ryoma_nicer-0.7.8.dist-info/METADATA
ryoma_nicer-0.7.8.dist-info/WHEEL
ryoma_nicer-0.7.8.dist-info/licenses/LICENSE
ryoma_nicer-0.7.8.dist-info/RECORD
