Metadata-Version: 2.4
Name: ryoma-nicer
Version: 0.7.8
Summary: a clone from the root project for Ryoma AI Platform – made compatible with Pydantic v2
License: Apache License
License-File: LICENSE
Requires-Python: >=3.10
Requires-Dist: black>=23.3.0
Requires-Dist: click>=8.0.0
Requires-Dist: coverage-badge>=1.1.2
Requires-Dist: flake8>=3.9.2
Requires-Dist: isort>=5.9.3
Requires-Dist: mypy>=0.910
Requires-Dist: openai-responses>=0.10.0
Requires-Dist: pip>=21.3.1
Requires-Dist: pydantic<3.0.0,>=2.0.0
Requires-Dist: pytest-cov>=5.0.0
Requires-Dist: pytest>=6.2.5
Requires-Dist: pyupgrade>=2.26.0
Requires-Dist: setuptools>=58.0.4
Requires-Dist: tabulate>=0.9.0
Provides-Extra: bigquery
Requires-Dist: gcsfs>=2025.3.2; extra == 'bigquery'
Requires-Dist: google-cloud-bigquery>=3.33.0; extra == 'bigquery'
